rickpy/__init__.py
rickpy-0.1.4.dist-info/LICENSE
rickpy-0.1.4.dist-info/METADATA
rickpy-0.1.4.dist-info/WHEEL
rickpy-0.1.4.dist-info/top_level.txt
rickpy-0.1.4.dist-info/RECORD
